posscore/__init__.py
posscore/scorer.py
posscore/tokenizers.py
posscore/util.py
posscore-0.0.1.dist-info/METADATA
posscore-0.0.1.dist-info/WHEEL
posscore-0.0.1.dist-info/top_level.txt
posscore-0.0.1.dist-info/RECORD
