Metadata-Version: 2.1
Name: posscore
Version: 0.0.1
Summary: This is a package for the POSSCORE metric.
Home-page: https://github.com/zy-liu/POSSCORE
Author: Zeyang Liu
Author-email: liuzeyang0001@gmail.com
License: UNKNOWN
Platform: UNKNOWN
Classifier: Programming Language :: Python :: 3
Classifier: License :: OSI Approved :: MIT License
Classifier: Operating System :: OS Independent
Requires-Python: >=3.6
Requires-Dist: nltk (>=3.4.3)
Requires-Dist: gensim (>=3.8.0)
Requires-Dist: numpy
